{
    "searchParameters": {
        "q": "Electronic components",
        "type": "images",
        "num": 100,
        "engine": "google"
    },
    "images": [
        {
            "title": "What Are Electronic Components? Classification And ...",
            "imageUrl": "https://thetech.com.vn/wp-content/uploads/2023/05/Electronic-components-1.png",
            "imageWidth": 800,
            "imageHeight": 303,
            "thumbnailUrl": "https://encrypted-tbn0.gstatic.com/images?q=tbn:ANd9GcTcWJjTulLwEFlOeefY8Dp1P6vXJkDCIZsO0w&s",
            "thumbnailWidth": 365,
            "thumbnailHeight": 138,
            "source": "Thetech",
            "domain": "thetech.com.vn",
            "link": "https://thetech.com.vn/en/what-are-electronic-components-classification-and-application/",
            "googleUrl": "https://www.google.com/imgres?imgurl=https%3A%2F%2Fthetech.com.vn%2Fwp-content%2Fuploads%2F2023%2F05%2FElectronic-components-1.png&tbnid=mUKb-_5qp8JaEM&imgrefurl=https%3A%2F%2Fthetech.com.vn%2Fen%2Fwhat-are-electronic-components-classification-and-application%2F&docid=03kGfe1Dh5q-3M&w=800&h=303",
            "position": 96
        },
        {
            "title": "A Deep Dive into 14 Essential Electrical Components ...",
            "imageUrl": "https://www.microchipusa.com/wp-content/uploads/2023/04/Electrical-Components-1-930x620-1.png",
            "imageWidth": 930,
            "imageHeight": 620,
            "thumbnailUrl": "https://encrypted-tbn0.gstatic.com/images?q=tbn:ANd9GcS3sg2U2eOsG8KUfjN5Pdl1_kn2tjf8zeN-ug&s",
            "thumbnailWidth": 275,
            "thumbnailHeight": 183,
            "source": "Microchip USA",
            "domain": "www.microchipusa.com",
            "link": "https://www.microchipusa.com/electrical-components/a-deep-dive-into-14-essential-electrical-components/",
            "googleUrl": "https://www.google.com/imgres?imgurl=https%3A%2F%2Fwww.microchipusa.com%2Fwp-content%2Fuploads%2F2023%2F04%2FElectrical-Components-1-930x620-1.png&tbnid=U2Y4yaT_lwRZVM&imgrefurl=https%3A%2F%2Fwww.microchipusa.com%2Felectrical-components%2Fa-deep-dive-into-14-essential-electrical-components%2F&docid=7CNeiNpT4BqJ4M&w=930&h=620",
            "position": 97
        },
        {
            "title": "Electronic Components - SARCNET",
            "imageUrl": "https://www.sarcnet.org/images/datasheet.jpg",
            "imageWidth": 710,
            "imageHeight": 666,
            "thumbnailUrl": "https://encrypted-tbn0.gstatic.com/images?q=tbn:ANd9GcTrJJvLMP_8HEtayPghs-LcTKHqHl3Ve2ou8Q&s",
            "thumbnailWidth": 232,
            "thumbnailHeight": 217,
            "source": "sarcnet",
            "domain": "www.sarcnet.org",
            "link": "https://www.sarcnet.org/electronic-components.html",
            "googleUrl": "https://www.google.com/imgres?imgurl=https%3A%2F%2Fwww.sarcnet.org%2Fimages%2Fdatasheet.jpg&tbnid=i1WM1xBo8O7mBM&imgrefurl=https%3A%2F%2Fwww.sarcnet.org%2Felectronic-components.html&docid=RtQSMcexEh6ASM&w=710&h=666",
            "position": 98
        },
        {
            "title": "Basic Electronics Tutorial",
            "imageUrl": "https://www.tutorialspoint.com/basic_electronics/images/basic_electronics_tutorial.jpg",
            "imageWidth": 700,
            "imageHeight": 250,
            "thumbnailUrl": "https://encrypted-tbn0.gstatic.com/images?q=tbn:ANd9GcTAznwbmTaTK79UbToL57hHNiKGOd1NyaFvzw&s",
            "thumbnailWidth": 376,
            "thumbnailHeight": 134,
            "source": "TutorialsPoint",
            "domain": "www.tutorialspoint.com",
            "link": "https://www.tutorialspoint.com/basic_electronics/index.htm",
            "googleUrl": "https://www.google.com/imgres?imgurl=https%3A%2F%2Fwww.tutorialspoint.com%2Fbasic_electronics%2Fimages%2Fbasic_electronics_tutorial.jpg&tbnid=ngKhNG2xj-jcbM&imgrefurl=https%3A%2F%2Fwww.tutorialspoint.com%2Fbasic_electronics%2Findex.htm&docid=2q7OcTCUF9AymM&w=700&h=250",
            "position": 99
        },
        {
            "title": "Electronic Components - Definition, Types and Working",
            "imageUrl": "https://media.geeksforgeeks.org/wp-content/uploads/20231113114041/Electronic-Components-660.png",
            "imageWidth": 660,
            "imageHeight": 330,
            "thumbnailUrl": "https://encrypted-tbn0.gstatic.com/images?q=tbn:ANd9GcSLlxXxf51xeQI4_d7Rx3tQBL1OWZ0x1Y5I5Q&s",
            "thumbnailWidth": 318,
            "thumbnailHeight": 159,
            "source": "GeeksforGeeks",
            "domain": "www.geeksforgeeks.org",
            "link": "https://www.geeksforgeeks.org/electronic-components/",
            "googleUrl": "https://www.google.com/imgres?imgurl=https%3A%2F%2Fmedia.geeksforgeeks.org%2Fwp-content%2Fuploads%2F20231113114041%2FElectronic-Components-660.png&tbnid=gt_mYDf04Zez3M&imgrefurl=https%3A%2F%2Fwww.geeksforgeeks.org%2Felectronic-components%2F&docid=cBaoJE3nuGcssM&w=660&h=330",
            "position": 100
        }
    ],
    "credits": 2
}