{
    "searchParameters": {
        "q": "Gaming Consoles",
        "type": "images",
        "num": 100,
        "engine": "google"
    },
    "images": [   
        {
            "title": "What was the first gaming console you owned and what year ...",
            "imageUrl": "https://i.redd.it/fj74dzeqv5u91.jpg",
            "imageWidth": 800,
            "imageHeight": 477,
            "thumbnailUrl": "https://encrypted-tbn0.gstatic.com/images?q=tbn:ANd9GcQPdn38Qzuy4s9qaPH6okAK0SfO57-xwJOiSg&s",
            "thumbnailWidth": 291,
            "thumbnailHeight": 173,
            "source": "Reddit",
            "domain": "www.reddit.com",
            "link": "https://www.reddit.com/r/GenZ/comments/y5fmf8/what_was_the_first_gaming_console_you_owned_and/",
            "googleUrl": "https://www.google.com/imgres?imgurl=https%3A%2F%2Fi.redd.it%2Ffj74dzeqv5u91.jpg&tbnid=juI9qDkS95B8yM&imgrefurl=https%3A%2F%2Fwww.reddit.com%2Fr%2FGenZ%2Fcomments%2Fy5fmf8%2Fwhat_was_the_first_gaming_console_you_owned_and%2F&docid=lSJmht95DocjWM&w=800&h=477",
            "position": 93
        },
        {
            "title": "The Best Handheld Game Consoles (for Travel, Escapism, and ...",
            "imageUrl": "https://www.vice.com/wp-content/uploads/sites/2/2024/02/1707172190074-screen-shot-2024-02-05-at-52945-pm.png?w=556",
            "imageWidth": 556,
            "imageHeight": 622,
            "thumbnailUrl": "https://encrypted-tbn0.gstatic.com/images?q=tbn:ANd9GcTJaG4Q7vMF1rOICtfzjD1UBsXgDoPQFXWFGg&s",
            "thumbnailWidth": 212,
            "thumbnailHeight": 237,
            "source": "VICE",
            "domain": "www.vice.com",
            "link": "https://www.vice.com/en/article/best-handheld-game-consoles/",
            "googleUrl": "https://www.google.com/imgres?imgurl=https%3A%2F%2Fwww.vice.com%2Fwp-content%2Fuploads%2Fsites%2F2%2F2024%2F02%2F1707172190074-screen-shot-2024-02-05-at-52945-pm.png%3Fw%3D556&tbnid=ENxK5raLyUMk8M&imgrefurl=https%3A%2F%2Fwww.vice.com%2Fen%2Farticle%2Fbest-handheld-game-consoles%2F&docid=DfrlpxSFX4OiWM&w=556&h=622",
            "position": 94
        },
        {
            "title": "Gaming PC vs gaming console: Which one should you buy ...",
            "imageUrl": "https://images.hindustantimes.com/img/2024/08/02/550x309/Gaming-PC-vs-consoles_hero_1722572863091_1722572875020.jpg",
            "imageWidth": 549,
            "imageHeight": 309,
            "thumbnailUrl": "https://encrypted-tbn0.gstatic.com/images?q=tbn:ANd9GcTJW5_SniahLN7aWfHQMMQ8RikDLIIYbohDBw&s",
            "thumbnailWidth": 299,
            "thumbnailHeight": 168,
            "source": "Hindustan Times",
            "domain": "www.hindustantimes.com",
            "link": "https://www.hindustantimes.com/technology/gaming-pc-vs-gaming-console-which-one-should-you-buy-101722572143505.html",
            "googleUrl": "https://www.google.com/imgres?imgurl=https%3A%2F%2Fimages.hindustantimes.com%2Fimg%2F2024%2F08%2F02%2F550x309%2FGaming-PC-vs-consoles_hero_1722572863091_1722572875020.jpg&tbnid=Z3r3_0B1yAMZ8M&imgrefurl=https%3A%2F%2Fwww.hindustantimes.com%2Ftechnology%2Fgaming-pc-vs-gaming-console-which-one-should-you-buy-101722572143505.html&docid=CQNKh2dL1Sjw5M&w=549&h=309",
            "position": 95
        },
        {
            "title": "Best Handheld Game Consoles of 2024 - CNET",
            "imageUrl": "https://www.cnet.com/a/img/resize/2fae0a6a6ffe938a099c036ce273f63afcc5f281/hub/2023/02/10/5e72242c-2b8e-4d9f-a200-aac10d320c5f/razer-edge-hot-wheels.jpg?auto=webp&fit=crop&height=360&width=640",
            "imageWidth": 640,
            "imageHeight": 360,
            "thumbnailUrl": "https://encrypted-tbn0.gstatic.com/images?q=tbn:ANd9GcSg32VLRXunuNB2gJIEg2qd7M_xgJSlr3S0bg&s",
            "thumbnailWidth": 300,
            "thumbnailHeight": 168,
            "source": "CNET",
            "domain": "www.cnet.com",
            "link": "https://www.cnet.com/tech/gaming/best-handheld-game-console/",
            "googleUrl": "https://www.google.com/imgres?imgurl=https%3A%2F%2Fwww.cnet.com%2Fa%2Fimg%2Fresize%2F2fae0a6a6ffe938a099c036ce273f63afcc5f281%2Fhub%2F2023%2F02%2F10%2F5e72242c-2b8e-4d9f-a200-aac10d320c5f%2Frazer-edge-hot-wheels.jpg%3Fauto%3Dwebp%26fit%3Dcrop%26height%3D360%26width%3D640&tbnid=xbWHW_JXnVIs6M&imgrefurl=https%3A%2F%2Fwww.cnet.com%2Ftech%2Fgaming%2Fbest-handheld-game-console%2F&docid=o_8N-TbSIUq4nM&w=640&h=360",
            "position": 96
        },
        {
            "title": "The best retro game consoles | Creative Bloq",
            "imageUrl": "https://cdn.mos.cms.futurecdn.net/2voEFneih86Rr6VkFcq5Ag-320-80.jpg",
            "imageWidth": 320,
            "imageHeight": 320,
            "thumbnailUrl": "https://encrypted-tbn0.gstatic.com/images?q=tbn:ANd9GcRPL10ciJU7pDu70GC6XcpcJ8sqU776L35smw&s",
            "thumbnailWidth": 225,
            "thumbnailHeight": 225,
            "source": "Creative Bloq",
            "domain": "www.creativebloq.com",
            "link": "https://www.creativebloq.com/buying-guides/best-retro-gaming-consoles",
            "googleUrl": "https://www.google.com/imgres?imgurl=https%3A%2F%2Fcdn.mos.cms.futurecdn.net%2F2voEFneih86Rr6VkFcq5Ag-320-80.jpg&tbnid=tMWY0w_frmmMoM&imgrefurl=https%3A%2F%2Fwww.creativebloq.com%2Fbuying-guides%2Fbest-retro-gaming-consoles&docid=dn0AHwnMdigIhM&w=320&h=320",
            "position": 97
        },
        {
            "title": "The best video game consoles for 2024 | Digital Trends",
            "imageUrl": "https://www.digitaltrends.com/wp-content/uploads/2023/11/ps5-on-table.jpg?fit=720%2C720&p=1",
            "imageWidth": 719,
            "imageHeight": 405,
            "thumbnailUrl": "https://encrypted-tbn0.gstatic.com/images?q=tbn:ANd9GcSpR19uawDdz8Kb_ts-AABwT4coWR0dDuDCvw&s",
            "thumbnailWidth": 299,
            "thumbnailHeight": 168,
            "source": "Digital Trends",
            "domain": "www.digitaltrends.com",
            "link": "https://www.digitaltrends.com/gaming/best-gaming-consoles/",
            "googleUrl": "https://www.google.com/imgres?imgurl=https%3A%2F%2Fwww.digitaltrends.com%2Fwp-content%2Fuploads%2F2023%2F11%2Fps5-on-table.jpg%3Ffit%3D720%252C720%26p%3D1&tbnid=yg2DusXw4TlsfM&imgrefurl=https%3A%2F%2Fwww.digitaltrends.com%2Fgaming%2Fbest-gaming-consoles%2F&docid=4DbK5X8Vn2nLrM&w=719&h=405",
            "position": 98
        }
    ],
    "credits": 2
}