{
    "searchParameters": {
        "q": "Speakers",
        "type": "images",
        "num": 100,
        "engine": "google"
    },
    "images": [
        {
            "title": "6 Best Computer Speakers 2024 | The Strategist",
            "imageUrl": "https://pyxis.nymag.com/v1/imgs/42b/68b/853835b7fc516c182aee05982a05d5ad5e-216speakers.2x.rsocial.w600.jpg",
            "imageWidth": 1200,
            "imageHeight": 630,
            "thumbnailUrl": "https://encrypted-tbn0.gstatic.com/images?q=tbn:ANd9GcTfRn7Yy0yzAtyLoZVzXTFDn36avY7O8BQPrA&s",
            "thumbnailWidth": 310,
            "thumbnailHeight": 163,
            "source": "New York Magazine",
            "domain": "nymag.com",
            "link": "https://nymag.com/strategist/article/best-computer-speakers.html",
            "googleUrl": "https://www.google.com/imgres?imgurl=https%3A%2F%2Fpyxis.nymag.com%2Fv1%2Fimgs%2F42b%2F68b%2F853835b7fc516c182aee05982a05d5ad5e-216speakers.2x.rsocial.w600.jpg&tbnid=wvXcL5okjP8JAM&imgrefurl=https%3A%2F%2Fnymag.com%2Fstrategist%2Farticle%2Fbest-computer-speakers.html&docid=AJ0I8fuL8ZkDfM&w=1200&h=630",
            "position": 56
        },
        {
            "title": "The best outdoor speakers of 2024 to pump up your parties ...",
            "imageUrl": "https://s.yimg.com/os/creatr-uploaded-images/2022-10/74c2d400-4975-11ed-9fbf-0d3c67779ebd",
            "imageWidth": 1200,
            "imageHeight": 700,
            "thumbnailUrl": "https://encrypted-tbn0.gstatic.com/images?q=tbn:ANd9GcRzurEk2O10DMjxjCEJtYEM4-b32hz4-Cfjyg&s",
            "thumbnailWidth": 294,
            "thumbnailHeight": 171,
            "source": "Yahoo",
            "domain": "www.yahoo.com",
            "link": "https://www.yahoo.com/tech/best-outdoor-speakers-185322069.html",
            "googleUrl": "https://www.google.com/imgres?imgurl=https%3A%2F%2Fs.yimg.com%2Fos%2Fcreatr-uploaded-images%2F2022-10%2F74c2d400-4975-11ed-9fbf-0d3c67779ebd&tbnid=V5WEeUUmw6RUbM&imgrefurl=https%3A%2F%2Fwww.yahoo.com%2Ftech%2Fbest-outdoor-speakers-185322069.html&docid=t9lc61RRjnswGM&w=1200&h=700",
            "position": 57
        },
        {
            "title": "The 5 Best Bookshelf Speakers for Most Stereos | Reviews by ...",
            "imageUrl": "https://cdn.thewirecutter.com/wp-content/media/2023/06/bookshelfspeakers-2048px-5399.jpg?auto=webp&quality=75&width=1024",
            "imageWidth": 1024,
            "imageHeight": 683,
            "thumbnailUrl": "https://encrypted-tbn0.gstatic.com/images?q=tbn:ANd9GcRJuqga8P-V2FrW8Sk5jI8a5hhrI-2-rzqavg&s",
            "thumbnailWidth": 275,
            "thumbnailHeight": 183,
            "source": "The New York Times",
            "domain": "www.nytimes.com",
            "link": "https://www.nytimes.com/wirecutter/reviews/best-bookshelf-speakers/",
            "googleUrl": "https://www.google.com/imgres?imgurl=https%3A%2F%2Fcdn.thewirecutter.com%2Fwp-content%2Fmedia%2F2023%2F06%2Fbookshelfspeakers-2048px-5399.jpg%3Fauto%3Dwebp%26quality%3D75%26width%3D1024&tbnid=qFwegC7h-69ikM&imgrefurl=https%3A%2F%2Fwww.nytimes.com%2Fwirecutter%2Freviews%2Fbest-bookshelf-speakers%2F&docid=C9bcISZ6JGXU6M&w=1024&h=683",
            "position": 58
        },
        {
            "title": "Wireless HiFi Speakers | KEF USA",
            "imageUrl": "https://us.kef.com/cdn/shop/products/pdt-lsx2-lt-stn-pks01.png?v=1706084248&width=540",
            "imageWidth": 540,
            "imageHeight": 540,
            "thumbnailUrl": "https://encrypted-tbn0.gstatic.com/images?q=tbn:ANd9GcTE7bJ2vXX6yvTfdqYKCuZzpkFcMjF2hTjVjw&s",
            "thumbnailWidth": 225,
            "thumbnailHeight": 225,
            "source": "KEF",
            "domain": "us.kef.com",
            "link": "https://us.kef.com/collections/wireless-hifi-speakers",
            "googleUrl": "https://www.google.com/imgres?imgurl=https%3A%2F%2Fus.kef.com%2Fcdn%2Fshop%2Fproducts%2Fpdt-lsx2-lt-stn-pks01.png%3Fv%3D1706084248%26width%3D540&tbnid=8ewpGvhUOrIbEM&imgrefurl=https%3A%2F%2Fus.kef.com%2Fcollections%2Fwireless-hifi-speakers&docid=6s6Kv7wL-EglMM&w=540&h=540",
            "position": 59
        },
        {
            "title": "Personalized Wooden Beat Block Cell Phone Speaker (Free ...",
            "imageUrl": "https://themanregistry.com/wp-content/uploads/2017/02/Beat-Block-speakers-make-a-unique-gift-for-music-loving-groomsmen.jpg",
            "imageWidth": 550,
            "imageHeight": 550,
            "thumbnailUrl": "https://encrypted-tbn0.gstatic.com/images?q=tbn:ANd9GcRV52SSaBEfmFGd5Dxvqe4ZJoFTc5DIwGGgWQ&s",
            "thumbnailWidth": 224,
            "thumbnailHeight": 224,
            "source": "The Man Registry",
            "domain": "themanregistry.com",
            "link": "https://themanregistry.com/gift/personalized-wooden-beat-block-cell-phone-speaker/",
            "googleUrl": "https://www.google.com/imgres?imgurl=https%3A%2F%2Fthemanregistry.com%2Fwp-content%2Fuploads%2F2017%2F02%2FBeat-Block-speakers-make-a-unique-gift-for-music-loving-groomsmen.jpg&tbnid=qXQxAd_g0-WVcM&imgrefurl=https%3A%2F%2Fthemanregistry.com%2Fgift%2Fpersonalized-wooden-beat-block-cell-phone-speaker%2F&docid=pGVHV6mvXr4VIM&w=550&h=550",
            "position": 60
        },
        {
            "title": "Best Speakers of 2024 - CNET",
            "imageUrl": "https://www.cnet.com/a/img/resize/050869e18736a06e05688f86db3e3805215c2b63/hub/2021/05/13/d4445988-4e84-4652-abc5-dfc2924395fd/edifier-r1280db-2-3.png?auto=webp&format=pjpg&height=500",
            "imageWidth": 689,
            "imageHeight": 500,
            "thumbnailUrl": "https://encrypted-tbn0.gstatic.com/images?q=tbn:ANd9GcTE2r3-U4AE9WA-6aeukyKeDZMJ2dCLWFZt_Q&s",
            "thumbnailWidth": 264,
            "thumbnailHeight": 191,
            "source": "CNET",
            "domain": "www.cnet.com",
            "link": "https://www.cnet.com/tech/home-entertainment/best-speakers/",
            "googleUrl": "https://www.google.com/imgres?imgurl=https%3A%2F%2Fwww.cnet.com%2Fa%2Fimg%2Fresize%2F050869e18736a06e05688f86db3e3805215c2b63%2Fhub%2F2021%2F05%2F13%2Fd4445988-4e84-4652-abc5-dfc2924395fd%2Fedifier-r1280db-2-3.png%3Fauto%3Dwebp%26format%3Dpjpg%26height%3D500&tbnid=9wVsy6-CpU-QAM&imgrefurl=https%3A%2F%2Fwww.cnet.com%2Ftech%2Fhome-entertainment%2Fbest-speakers%2F&docid=IRXepeCxh5WZlM&w=689&h=500",
            "position": 61
        },
        {
            "title": "iLive Indoor Outdoor IPX6 Waterproof Bluetooth Wireless ...",
            "imageUrl": "https://images.thdstatic.com/productImages/1039a6c5-65f6-4170-84bc-d384b9cda127/svn/black-ilive-portable-audio-video-isbw240bdl-4f_600.jpg",
            "imageWidth": 600,
            "imageHeight": 600,
            "thumbnailUrl": "https://encrypted-tbn0.gstatic.com/images?q=tbn:ANd9GcSFKvb9gbi75QD7gmPSNCRIrYkAhTCWc4911w&s",
            "thumbnailWidth": 225,
            "thumbnailHeight": 225,
            "source": "The Home Depot",
            "domain": "www.homedepot.com",
            "link": "https://www.homedepot.com/p/iLive-Indoor-Outdoor-IPX6-Waterproof-Bluetooth-Wireless-Speakers-with-Removable-Stakes-in-Black-Set-of-2-ISBW240BDL/318697633",
            "googleUrl": "https://www.google.com/imgres?imgurl=https%3A%2F%2Fimages.thdstatic.com%2FproductImages%2F1039a6c5-65f6-4170-84bc-d384b9cda127%2Fsvn%2Fblack-ilive-portable-audio-video-isbw240bdl-4f_600.jpg&tbnid=advVNgSuPPSFtM&imgrefurl=https%3A%2F%2Fwww.homedepot.com%2Fp%2FiLive-Indoor-Outdoor-IPX6-Waterproof-Bluetooth-Wireless-Speakers-with-Removable-Stakes-in-Black-Set-of-2-ISBW240BDL%2F318697633&docid=gg0Sr8d3bvc4IM&w=600&h=600",
            "position": 62
        },
        {
            "title": "Acton III Bluetooth speaker with powerful sound & classic ...",
            "imageUrl": "https://images.ctfassets.net/javen7msabdh/5uklH1TitBKvNqgTADUmJU/05933b59c6d7439cd14df8d206b262d4/07-acton-iii-black-speakers-mobile.jpeg",
            "imageWidth": 748,
            "imageHeight": 934,
            "thumbnailUrl": "https://encrypted-tbn0.gstatic.com/images?q=tbn:ANd9GcTclfOV3O713iR0XwxHbTcRh9B85_TtdHbPcg&s",
            "thumbnailWidth": 201,
            "thumbnailHeight": 251,
            "source": "Marshall",
            "domain": "www.marshall.com",
            "link": "https://www.marshall.com/us/en/product/acton-iii?pid=1006008",
            "googleUrl": "https://www.google.com/imgres?imgurl=https%3A%2F%2Fimages.ctfassets.net%2Fjaven7msabdh%2F5uklH1TitBKvNqgTADUmJU%2F05933b59c6d7439cd14df8d206b262d4%2F07-acton-iii-black-speakers-mobile.jpeg&tbnid=ptuZQ9oHss5WUM&imgrefurl=https%3A%2F%2Fwww.marshall.com%2Fus%2Fen%2Fproduct%2Facton-iii%3Fpid%3D1006008&docid=46-2pkRRlL2E5M&w=748&h=934",
            "position": 63
        },
        {
            "title": "SoundLink Micro Waterproof Bluetooth Speaker | Bose",
            "imageUrl": "https://assets.bosecreative.com/transform/a48332aa-8e2d-49e3-bb3a-a9c39bdafb5b/SLMC_CC_Set_Pair_Bundle_RGB",
            "imageWidth": 2000,
            "imageHeight": 1527,
            "thumbnailUrl": "https://encrypted-tbn0.gstatic.com/images?q=tbn:ANd9GcTDUe37CL89hLF40loWcT82B2zxyYD_KU49rg&s",
            "thumbnailWidth": 257,
            "thumbnailHeight": 196,
            "source": "Bose",
            "domain": "www.bose.com",
            "link": "https://www.bose.com/p/speakers/bose-soundlink-micro-bluetooth-speaker/SLMC-SPEAKERWIRELESS.html",
            "googleUrl": "https://www.google.com/imgres?imgurl=https%3A%2F%2Fassets.bosecreative.com%2Ftransform%2Fa48332aa-8e2d-49e3-bb3a-a9c39bdafb5b%2FSLMC_CC_Set_Pair_Bundle_RGB&tbnid=SQbyqomCZpRVuM&imgrefurl=https%3A%2F%2Fwww.bose.com%2Fp%2Fspeakers%2Fbose-soundlink-micro-bluetooth-speaker%2FSLMC-SPEAKERWIRELESS.html&docid=N9huDxR8NTJ5mM&w=2000&h=1527",
            "position": 64
        },
        {
            "title": "Bose Surround Speakers | Bose",
            "imageUrl": "https://assets.bose.com/content/dam/Bose_DAM/Web/consumer_electronics/global/accessories/speakers/bose_surround_speakers/product_silo_images/bose_surround_speakers_black_EC_02.psd/jcr:content/renditions/cq5dam.web.1920.1920.png",
            "imageWidth": 1200,
            "imageHeight": 1022,
            "thumbnailUrl": "https://encrypted-tbn0.gstatic.com/images?q=tbn:ANd9GcTW3M4zbs_omBJ5PgxdMTPm-nv2d_m_7NUIYg&s",
            "thumbnailWidth": 243,
            "thumbnailHeight": 207,
            "source": "Bose",
            "domain": "www.boselatam.com",
            "link": "https://www.boselatam.com/en_ar/products/speakers/speaker_accessories/bose-surround-speakers.html",
            "googleUrl": "https://www.google.com/imgres?imgurl=https%3A%2F%2Fassets.bose.com%2Fcontent%2Fdam%2FBose_DAM%2FWeb%2Fconsumer_electronics%2Fglobal%2Faccessories%2Fspeakers%2Fbose_surround_speakers%2Fproduct_silo_images%2Fbose_surround_speakers_black_EC_02.psd%2Fjcr%3Acontent%2Frenditions%2Fcq5dam.web.1920.1920.png&tbnid=CNxpWU_8AV4uJM&imgrefurl=https%3A%2F%2Fwww.boselatam.com%2Fen_ar%2Fproducts%2Fspeakers%2Fspeaker_accessories%2Fbose-surround-speakers.html&docid=EIrEpdGk3sraQM&w=1200&h=1022",
            "position": 65
        },
        {
            "title": "CG3M Bookshelf Speaker – Rogersound Labs",
            "imageUrl": "https://rslspeakers.com/cdn/shop/files/CG3M-A-Badge-v1.0-1.png?v=1721094325&width=1214",
            "imageWidth": 1214,
            "imageHeight": 1214,
            "thumbnailUrl": "https://encrypted-tbn0.gstatic.com/images?q=tbn:ANd9GcSpsPpWQBMJSEQRFWH4MkqsfkVm3efw-6eHCA&s",
            "thumbnailWidth": 225,
            "thumbnailHeight": 225,
            "source": "Rogersound Labs",
            "domain": "rslspeakers.com",
            "link": "https://rslspeakers.com/products/cg3m-bookshelf-speaker",
            "googleUrl": "https://www.google.com/imgres?imgurl=https%3A%2F%2Frslspeakers.com%2Fcdn%2Fshop%2Ffiles%2FCG3M-A-Badge-v1.0-1.png%3Fv%3D1721094325%26width%3D1214&tbnid=N9dePzvUAhRRKM&imgrefurl=https%3A%2F%2Frslspeakers.com%2Fproducts%2Fcg3m-bookshelf-speaker&docid=Bwc2zG_VZt45wM&w=1214&h=1214",
            "position": 66
        },
        {
            "title": "The 8 Best Home Bluetooth Speakers - Fall 2024 - RTINGS.com",
            "imageUrl": "https://i.rtings.com/assets/pages/nyS7u7mM/best-home-bluetooth-speakers-20230901-2-medium.jpg?format=auto",
            "imageWidth": 1000,
            "imageHeight": 563,
            "thumbnailUrl": "https://encrypted-tbn0.gstatic.com/images?q=tbn:ANd9GcQVTwUlk4YXUvlQOfyY_gsaq4_KKMCbINI-tw&s",
            "thumbnailWidth": 299,
            "thumbnailHeight": 168,
            "source": "RTINGS.com",
            "domain": "www.rtings.com",
            "link": "https://www.rtings.com/speaker/reviews/best/by-usage/home",
            "googleUrl": "https://www.google.com/imgres?imgurl=https%3A%2F%2Fi.rtings.com%2Fassets%2Fpages%2FnyS7u7mM%2Fbest-home-bluetooth-speakers-20230901-2-medium.jpg%3Fformat%3Dauto&tbnid=HyYBJHHOJChK5M&imgrefurl=https%3A%2F%2Fwww.rtings.com%2Fspeaker%2Freviews%2Fbest%2Fby-usage%2Fhome&docid=Oli-vG3C3lw2eM&w=1000&h=563",
            "position": 67
        },
        {
            "title": "JBL Quantum Duo | PC Gaming Speakers | JBL PH",
            "imageUrl": "https://www.jbl.com.ph/on/demandware.static/-/Sites-masterCatalog_Harman/default/dw58ee323b/pdp/JBL_Quantum_Duo_Lifestyle_03_904x560px.png",
            "imageWidth": 904,
            "imageHeight": 560,
            "thumbnailUrl": "https://encrypted-tbn0.gstatic.com/images?q=tbn:ANd9GcSPb18YDIJ_7TmWzTMhxIwrmZRQB5CJxcFJPQ&s",
            "thumbnailWidth": 285,
            "thumbnailHeight": 177,
            "source": "www.jbl.com.ph",
            "domain": "www.jbl.com.ph",
            "link": "https://www.jbl.com.ph/gaming/QUANTUM+DUO-.html",
            "googleUrl": "https://www.google.com/imgres?imgurl=https%3A%2F%2Fwww.jbl.com.ph%2Fon%2Fdemandware.static%2F-%2FSites-masterCatalog_Harman%2Fdefault%2Fdw58ee323b%2Fpdp%2FJBL_Quantum_Duo_Lifestyle_03_904x560px.png&tbnid=DV723H1FbGDrpM&imgrefurl=https%3A%2F%2Fwww.jbl.com.ph%2Fgaming%2FQUANTUM%2BDUO-.html&docid=eIxUAN4n6TIamM&w=904&h=560",
            "position": 68
        },
        {
            "title": "The best speakers for 2024: sets for music, movies, and more ...",
            "imageUrl": "https://www.digitaltrends.com/wp-content/uploads/2023/08/BW-607-S3-Black.jpeg?fit=2200%2C1466&p=1",
            "imageWidth": 2200,
            "imageHeight": 1466,
            "thumbnailUrl": "https://encrypted-tbn0.gstatic.com/images?q=tbn:ANd9GcTOCBKGORF46ytRIyhw0wzme6Pa26Qo1WilSw&s",
            "thumbnailWidth": 275,
            "thumbnailHeight": 183,
            "source": "Digital Trends",
            "domain": "www.digitaltrends.com",
            "link": "https://www.digitaltrends.com/home-theater/best-speakers/",
            "googleUrl": "https://www.google.com/imgres?imgurl=https%3A%2F%2Fwww.digitaltrends.com%2Fwp-content%2Fuploads%2F2023%2F08%2FBW-607-S3-Black.jpeg%3Ffit%3D2200%252C1466%26p%3D1&tbnid=ivjdOKSQU5qhyM&imgrefurl=https%3A%2F%2Fwww.digitaltrends.com%2Fhome-theater%2Fbest-speakers%2F&docid=YUNqaq37-6VcdM&w=2200&h=1466",
            "position": 69
        },
        {
            "title": "The 5 Best Budget And Cheap Bluetooth Speakers - Fall 2024 ...",
            "imageUrl": "https://i.rtings.com/assets/pages/rYmHu8AR/best-cheap-and-budget-speakers20240418-medium.jpg?format=auto",
            "imageWidth": 1000,
            "imageHeight": 563,
            "thumbnailUrl": "https://encrypted-tbn0.gstatic.com/images?q=tbn:ANd9GcT_YjLgzhuAiNYPhu4lj5yvD6N4vwHM-zFggw&s",
            "thumbnailWidth": 299,
            "thumbnailHeight": 168,
            "source": "RTINGS.com",
            "domain": "www.rtings.com",
            "link": "https://www.rtings.com/speaker/reviews/best/by-price/cheap",
            "googleUrl": "https://www.google.com/imgres?imgurl=https%3A%2F%2Fi.rtings.com%2Fassets%2Fpages%2FrYmHu8AR%2Fbest-cheap-and-budget-speakers20240418-medium.jpg%3Fformat%3Dauto&tbnid=8KsofV76c7j0lM&imgrefurl=https%3A%2F%2Fwww.rtings.com%2Fspeaker%2Freviews%2Fbest%2Fby-price%2Fcheap&docid=GOXJ8Qd5OZnu9M&w=1000&h=563",
            "position": 70
        },
        {
            "title": "Best PC Speakers 2024: From Budget to Audiophile Bliss ...",
            "imageUrl": "https://cdn.mos.cms.futurecdn.net/N2S8Jxu3dASZ3vwZgYkNHQ.jpg",
            "imageWidth": 3474,
            "imageHeight": 1489,
            "thumbnailUrl": "https://encrypted-tbn0.gstatic.com/images?q=tbn:ANd9GcTxFljRvKKuUf2JuzkceDIX1MMiRuoq8ProDw&s",
            "thumbnailWidth": 343,
            "thumbnailHeight": 147,
            "source": "Tom's Hardware",
            "domain": "www.tomshardware.com",
            "link": "https://www.tomshardware.com/best-picks/best-pc-speakers",
            "googleUrl": "https://www.google.com/imgres?imgurl=https%3A%2F%2Fcdn.mos.cms.futurecdn.net%2FN2S8Jxu3dASZ3vwZgYkNHQ.jpg&tbnid=sQG3fze5RON0JM&imgrefurl=https%3A%2F%2Fwww.tomshardware.com%2Fbest-picks%2Fbest-pc-speakers&docid=OHjInL9S8SO_lM&w=3474&h=1489",
            "position": 71
        },
        {
            "title": "Loudspeaker - Wikipedia",
            "imageUrl": "https://upload.wikimedia.org/wikipedia/commons/0/0e/Electrodynamic-loudspeaker.png",
            "imageWidth": 524,
            "imageHeight": 955,
            "thumbnailUrl": "https://encrypted-tbn0.gstatic.com/images?q=tbn:ANd9GcQdM-SqWz3YmkNdkh3OnNcSo_yRGoNEdEmx_w&s",
            "thumbnailWidth": 166,
            "thumbnailHeight": 303,
            "source": "Wikipedia",
            "domain": "en.wikipedia.org",
            "link": "https://en.wikipedia.org/wiki/Loudspeaker",
            "googleUrl": "https://www.google.com/imgres?imgurl=https%3A%2F%2Fupload.wikimedia.org%2Fwikipedia%2Fcommons%2F0%2F0e%2FElectrodynamic-loudspeaker.png&tbnid=kF3PJfDPau7EWM&imgrefurl=https%3A%2F%2Fen.wikipedia.org%2Fwiki%2FLoudspeaker&docid=JaKVMhpnqCYD0M&w=524&h=955",
            "position": 72
        },
        {
            "title": "McIntosh Speakers - Home Audio and Home Theater Loudspeakers",
            "imageUrl": "https://www.mcintoshlabs.com/-/media/Images/mcintoshlabs/Products/Category/ALL-CATEGORY-IMAGES/Speakers.jpg?rev=92d20f4467d84715a9c2c0f4aa630345&revision=92d20f44-67d8-4715-a9c2-c0f4aa630345",
            "imageWidth": 1920,
            "imageHeight": 1000,
            "thumbnailUrl": "https://encrypted-tbn0.gstatic.com/images?q=tbn:ANd9GcS7ohXXjOUTLrBTpcuz-19el8fsDsJTKFwd_g&s",
            "thumbnailWidth": 311,
            "thumbnailHeight": 162,
            "source": "McIntosh",
            "domain": "www.mcintoshlabs.com",
            "link": "https://www.mcintoshlabs.com/products/speakers",
            "googleUrl": "https://www.google.com/imgres?imgurl=https%3A%2F%2Fwww.mcintoshlabs.com%2F-%2Fmedia%2FImages%2Fmcintoshlabs%2FProducts%2FCategory%2FALL-CATEGORY-IMAGES%2FSpeakers.jpg%3Frev%3D92d20f4467d84715a9c2c0f4aa630345%26revision%3D92d20f44-67d8-4715-a9c2-c0f4aa630345&tbnid=5r9TatAE2ha-xM&imgrefurl=https%3A%2F%2Fwww.mcintoshlabs.com%2Fproducts%2Fspeakers&docid=4pl5mGPbQAS53M&w=1920&h=1000",
            "position": 73
        },
        {
            "title": "Best Car Speakers & Accessories – OnlineCarStereo.com",
            "imageUrl": "https://www.onlinecarstereo.com/Images/LandingPages/Car-speakers-Full-Range-Car-Speakers.jpg",
            "imageWidth": 450,
            "imageHeight": 330,
            "thumbnailUrl": "https://encrypted-tbn0.gstatic.com/images?q=tbn:ANd9GcTJ_hiuPs8hOJcOWnkpagWINPYBcjl0mAkESA&s",
            "thumbnailWidth": 262,
            "thumbnailHeight": 192,
            "source": "Onlinecarstereo.com",
            "domain": "www.onlinecarstereo.com",
            "link": "https://www.onlinecarstereo.com/category/128/Car_Speakers.aspx",
            "googleUrl": "https://www.google.com/imgres?imgurl=https%3A%2F%2Fwww.onlinecarstereo.com%2FImages%2FLandingPages%2FCar-speakers-Full-Range-Car-Speakers.jpg&tbnid=Hf_EoVYct9A5kM&imgrefurl=https%3A%2F%2Fwww.onlinecarstereo.com%2Fcategory%2F128%2FCar_Speakers.aspx&docid=M7xwn3DpPb0PdM&w=450&h=330",
            "position": 74
        },
        {
            "title": "Home Theater Sound Systems | Polk Audio",
            "imageUrl": "https://www.polkaudio.com/on/demandware.static/-/Library-Sites-polk_northamerica_shared/default/dw6be1b397/navigation/NavHighlight_HomeSpeakers.jpg",
            "imageWidth": 1500,
            "imageHeight": 900,
            "thumbnailUrl": "https://encrypted-tbn0.gstatic.com/images?q=tbn:ANd9GcSZAOxCg5hyPoIMSnWMSAdrLsHsaU0Cus8jPw&s",
            "thumbnailWidth": 290,
            "thumbnailHeight": 174,
            "source": "Polk Audio",
            "domain": "www.polkaudio.com",
            "link": "https://www.polkaudio.com/en-us/category/home-speakers/home-theater-systems/",
            "googleUrl": "https://www.google.com/imgres?imgurl=https%3A%2F%2Fwww.polkaudio.com%2Fon%2Fdemandware.static%2F-%2FLibrary-Sites-polk_northamerica_shared%2Fdefault%2Fdw6be1b397%2Fnavigation%2FNavHighlight_HomeSpeakers.jpg&tbnid=2RiLoWtm9NzMAM&imgrefurl=https%3A%2F%2Fwww.polkaudio.com%2Fen-us%2Fcategory%2Fhome-speakers%2Fhome-theater-systems%2F&docid=P1Gqz6DR5z7TcM&w=1500&h=900",
            "position": 75
        },
        {
            "title": "Bobtot Surround Sound Systems Wireless Rear Satellite Speakers - 800W  6.5inch Subwoofer 5.1/2.1 Channel Home Theater Systems with HDMI ARC  Optical ...",
            "imageUrl": "https://m.media-amazon.com/images/I/71ezEeucLaL.jpg",
            "imageWidth": 1600,
            "imageHeight": 1600,
            "thumbnailUrl": "https://encrypted-tbn0.gstatic.com/images?q=tbn:ANd9GcSrs3GaEP9YPi-PHMnRoTt5tw3rKxRO4aZ_jQ&s",
            "thumbnailWidth": 225,
            "thumbnailHeight": 225,
            "source": "Amazon.com",
            "domain": "www.amazon.com",
            "link": "https://www.amazon.com/Bobtot-Surround-Wireless-Satellite-Speakers/dp/B0CP56567T",
            "googleUrl": "https://www.google.com/imgres?imgurl=https%3A%2F%2Fm.media-amazon.com%2Fimages%2FI%2F71ezEeucLaL.jpg&tbnid=1HawIzp1BSxaDM&imgrefurl=https%3A%2F%2Fwww.amazon.com%2FBobtot-Surround-Wireless-Satellite-Speakers%2Fdp%2FB0CP56567T&docid=fZZYsiBfU7tXwM&w=1600&h=1600",
            "position": 76
        },
        {
            "title": "Products | Kanto Audio",
            "imageUrl": "https://www.kantoaudio.com/wp-content/uploads/yu4-lifestyle-banner-768x432.jpg",
            "imageWidth": 768,
            "imageHeight": 432,
            "thumbnailUrl": "https://encrypted-tbn0.gstatic.com/images?q=tbn:ANd9GcRqO6SXkj-O0UfWvVByengcJhyqiajnFdP3pA&s",
            "thumbnailWidth": 300,
            "thumbnailHeight": 168,
            "source": "Kanto Audio",
            "domain": "www.kantoaudio.com",
            "link": "https://www.kantoaudio.com/products/",
            "googleUrl": "https://www.google.com/imgres?imgurl=https%3A%2F%2Fwww.kantoaudio.com%2Fwp-content%2Fuploads%2Fyu4-lifestyle-banner-768x432.jpg&tbnid=lSjGPwIYXUgNRM&imgrefurl=https%3A%2F%2Fwww.kantoaudio.com%2Fproducts%2F&docid=NSSVoMJXnnP9oM&w=768&h=432",
            "position": 77
        },
        {
            "title": "The 21 Best Bluetooth Speakers in 2021 | Pitchfork",
            "imageUrl": "https://media.pitchfork.com/photos/60ba7b0442b81a6a8412188a/4:3/w_1064,h_798,c_limit/indoor%20bluetooth%20header%20copy.png",
            "imageWidth": 1064,
            "imageHeight": 798,
            "thumbnailUrl": "https://encrypted-tbn0.gstatic.com/images?q=tbn:ANd9GcQKxvg4ThAUP9fd3O3XbH36tkEP-ojzVy8UPQ&s",
            "thumbnailWidth": 259,
            "thumbnailHeight": 194,
            "source": "Pitchfork",
            "domain": "pitchfork.com",
            "link": "https://pitchfork.com/features/lists-and-guides/best-bluetooth-speakers-home/",
            "googleUrl": "https://www.google.com/imgres?imgurl=https%3A%2F%2Fmedia.pitchfork.com%2Fphotos%2F60ba7b0442b81a6a8412188a%2F4%3A3%2Fw_1064%2Ch_798%2Cc_limit%2Findoor%2520bluetooth%2520header%2520copy.png&tbnid=sN9icM5xw4DeXM&imgrefurl=https%3A%2F%2Fpitchfork.com%2Ffeatures%2Flists-and-guides%2Fbest-bluetooth-speakers-home%2F&docid=YWpmQbvNHzKi1M&w=1064&h=798",
            "position": 78
        },
        {
            "title": "Portable Bluetooth and Party Speakers - Sharp Europe",
            "imageUrl": "https://res.cloudinary.com/sharp-consumer-eu/image/fetch/w_2000,f_auto/https://www.sharpconsumer.com/wp-content/uploads/2020/09/speakers%E2%80%93-2.jpg",
            "imageWidth": 2000,
            "imageHeight": 600,
            "thumbnailUrl": "https://encrypted-tbn0.gstatic.com/images?q=tbn:ANd9GcSqtvKbNBSlU4_rWGbplAnUry96COvv4WGbng&s",
            "thumbnailWidth": 410,
            "thumbnailHeight": 123,
            "source": "Sharp Consumer Products Europe - Sharp Europe",
            "domain": "www.sharpconsumer.com",
            "link": "https://www.sharpconsumer.com/electronics/audio/speakers/",
            "googleUrl": "https://www.google.com/imgres?imgurl=https%3A%2F%2Fres.cloudinary.com%2Fsharp-consumer-eu%2Fimage%2Ffetch%2Fw_2000%2Cf_auto%2Fhttps%3A%2F%2Fwww.sharpconsumer.com%2Fwp-content%2Fuploads%2F2020%2F09%2Fspeakers%25E2%2580%2593-2.jpg&tbnid=a38XJfeLiLgCaM&imgrefurl=https%3A%2F%2Fwww.sharpconsumer.com%2Felectronics%2Faudio%2Fspeakers%2F&docid=y4HmAeImRlaI8M&w=2000&h=600",
            "position": 79
        },
        {
            "title": "CG3M Bookshelf Speaker – Rogersound Labs",
            "imageUrl": "https://rslspeakers.com/cdn/shop/files/CG3M-Rear-Angled-WhiteBG-800px.png?v=1721094173&width=1214",
            "imageWidth": 999,
            "imageHeight": 1500,
            "thumbnailUrl": "https://encrypted-tbn0.gstatic.com/images?q=tbn:ANd9GcQ36wMlrZWrfDTgIpEbNTb7cHhaXYapg9SsHw&s",
            "thumbnailWidth": 183,
            "thumbnailHeight": 275,
            "source": "Rogersound Labs",
            "domain": "rslspeakers.com",
            "link": "https://rslspeakers.com/products/cg3m-bookshelf-speaker",
            "googleUrl": "https://www.google.com/imgres?imgurl=https%3A%2F%2Frslspeakers.com%2Fcdn%2Fshop%2Ffiles%2FCG3M-Rear-Angled-WhiteBG-800px.png%3Fv%3D1721094173%26width%3D1214&tbnid=kWm65nysex8tPM&imgrefurl=https%3A%2F%2Frslspeakers.com%2Fproducts%2Fcg3m-bookshelf-speaker&docid=Bwc2zG_VZt45wM&w=999&h=1500",
            "position": 80
        },
        {
            "title": "SYMFONISK Sonos WiFi bookshelf speaker, black smart/gen 2 - IKEA",
            "imageUrl": "https://www.ikea.com/us/en/images/products/symfonisk-sonos-wifi-bookshelf-speaker-black-smart-gen-2__1025506_pe834047_s5.jpg",
            "imageWidth": 1400,
            "imageHeight": 1400,
            "thumbnailUrl": "https://encrypted-tbn0.gstatic.com/images?q=tbn:ANd9GcRxfnEG2wuEUvNDL9Y3taHZ9TqrLXMrUshMaw&s",
            "thumbnailWidth": 225,
            "thumbnailHeight": 225,
            "source": "IKEA",
            "domain": "www.ikea.com",
            "link": "https://www.ikea.com/us/en/p/symfonisk-sonos-wifi-bookshelf-speaker-black-smart-gen-2-20506584/",
            "googleUrl": "https://www.google.com/imgres?imgurl=https%3A%2F%2Fwww.ikea.com%2Fus%2Fen%2Fimages%2Fproducts%2Fsymfonisk-sonos-wifi-bookshelf-speaker-black-smart-gen-2__1025506_pe834047_s5.jpg&tbnid=OHYthaYncxjBzM&imgrefurl=https%3A%2F%2Fwww.ikea.com%2Fus%2Fen%2Fp%2Fsymfonisk-sonos-wifi-bookshelf-speaker-black-smart-gen-2-20506584%2F&docid=Q-X3BPjzkwfeFM&w=1400&h=1400",
            "position": 81
        },
        {
            "title": "The 5 Best Bookshelf Speakers for Most Stereos | Reviews by ...",
            "imageUrl": "https://cdn.thewirecutter.com/wp-content/media/2024/04/bookshelfspeakers-2048px-nogrille.jpg?auto=webp&quality=75&width=1024",
            "imageWidth": 1024,
            "imageHeight": 683,
            "thumbnailUrl": "https://encrypted-tbn0.gstatic.com/images?q=tbn:ANd9GcS3IfBo93NrJuadt9MVorz63A3jR2R2_pmU-Q&s",
            "thumbnailWidth": 275,
            "thumbnailHeight": 183,
            "source": "The New York Times",
            "domain": "www.nytimes.com",
            "link": "https://www.nytimes.com/wirecutter/reviews/best-bookshelf-speakers/",
            "googleUrl": "https://www.google.com/imgres?imgurl=https%3A%2F%2Fcdn.thewirecutter.com%2Fwp-content%2Fmedia%2F2024%2F04%2Fbookshelfspeakers-2048px-nogrille.jpg%3Fauto%3Dwebp%26quality%3D75%26width%3D1024&tbnid=6sZUXboWxmnD5M&imgrefurl=https%3A%2F%2Fwww.nytimes.com%2Fwirecutter%2Freviews%2Fbest-bookshelf-speakers%2F&docid=C9bcISZ6JGXU6M&w=1024&h=683",
            "position": 82
        },
        {
            "title": "6 Best Computer Speakers 2024 | The Strategist",
            "imageUrl": "https://pyxis.nymag.com/v1/imgs/f66/8ff/fba6042394150e7301c49b131ec967b972.rsquare.w600.jpg",
            "imageWidth": 600,
            "imageHeight": 600,
            "thumbnailUrl": "https://encrypted-tbn0.gstatic.com/images?q=tbn:ANd9GcR0MlPMAzwNoB5zFFYM0cBJ6kL2j4UM2emfCQ&s",
            "thumbnailWidth": 225,
            "thumbnailHeight": 225,
            "source": "New York Magazine",
            "domain": "nymag.com",
            "link": "https://nymag.com/strategist/article/best-computer-speakers.html",
            "googleUrl": "https://www.google.com/imgres?imgurl=https%3A%2F%2Fpyxis.nymag.com%2Fv1%2Fimgs%2Ff66%2F8ff%2Ffba6042394150e7301c49b131ec967b972.rsquare.w600.jpg&tbnid=AuxMSpKH_2oiSM&imgrefurl=https%3A%2F%2Fnymag.com%2Fstrategist%2Farticle%2Fbest-computer-speakers.html&docid=AJ0I8fuL8ZkDfM&w=600&h=600",
            "position": 83
        }
    ],
    "credits": 2
}